LICENSE
MANIFEST.in
README
setup.py
chiki_mongoengine/__init__.py
chiki_mongoengine/fields.py
chiki_mongoengine/generators.py
chiki_mongoengine/pagination.py
chiki_mongoengine/storages.py
chiki_mongoengine.egg-info/PKG-INFO
chiki_mongoengine.egg-info/SOURCES.txt
chiki_mongoengine.egg-info/dependency_links.txt
chiki_mongoengine.egg-info/not-zip-safe
chiki_mongoengine.egg-info/requires.txt
chiki_mongoengine.egg-info/top_level.txt