Metadata-Version: 1.0
Name: chiki-mongoengine
Version: 0.0.2
Summary: chiki mongoengine libs.
Home-page: https://github.com/endsh/chiki-mongoengine
Author: Linshao
Author-email: 438985635@qq.com
License: UNKNOWN
Platform: any
